userefuzz/__init__.py
userefuzz/__main__.py
userefuzz-2.2.0.dist-info/LICENSE
userefuzz-2.2.0.dist-info/METADATA
userefuzz-2.2.0.dist-info/WHEEL
userefuzz-2.2.0.dist-info/entry_points.txt
userefuzz-2.2.0.dist-info/top_level.txt
userefuzz-2.2.0.dist-info/RECORD
