Metadata-Version: 2.1
Name: userefuzz
Version: 2.2.0
Summary: User-Agent and Referer Header SQLI Fuzzer
Home-page: https://github.com/root-tanishq/userefuzz
Author: Tanishq Rathore
License: MIT
Classifier: Programming Language :: Python :: 3
License-File: LICENSE
Requires-Dist: colorama
Requires-Dist: requests
